metrecord/__init__.py
metrecord/__version__.py
metrecord/api.py
metrecord/exceptions.py
metrecord-0.0.2.dist-info/METADATA
metrecord-0.0.2.dist-info/WHEEL
metrecord-0.0.2.dist-info/top_level.txt
metrecord-0.0.2.dist-info/RECORD
